Metadata-Version: 2.1
Name: trBroker
Version: 0.0.2
Summary: Python module to onboard the TR broker platform
Author: Manish Uniyal
Author-email: uniyalmanish578@gmail.com
